pylabnet/README.md
pylabnet/__init__.py
pylabnet/gui/__init__.py
pylabnet/gui/output_interface.py
pylabnet/gui/igui/__init__.py
pylabnet/gui/igui/iplot.py
pylabnet/gui/pyqt/__init__.py
pylabnet/gui/pyqt/external_gui.py
pylabnet/gui/pyqt/gui_handler.py
pylabnet/gui/pyqt/gui_windowbuilder.py
pylabnet/gui/pyqt/gui_windowbuilder_test.py
pylabnet/gui/pyqt/custom_icons/add_pulse.svg
pylabnet/gui/pyqt/gui_templates/Confluence_GUI_Test.ui
pylabnet/gui/pyqt/gui_templates/__init__.py
pylabnet/gui/pyqt/gui_templates/add_pulse.svg
pylabnet/gui/pyqt/gui_templates/add_pulseblock.svg
pylabnet/gui/pyqt/gui_templates/add_var.svg
pylabnet/gui/pyqt/gui_templates/aom_toptica.ui
pylabnet/gui/pyqt/gui_templates/count_monitor.ui
pylabnet/gui/pyqt/gui_templates/count_monitor_combined.ui
pylabnet/gui/pyqt/gui_templates/cqed_fit_params.ui
pylabnet/gui/pyqt/gui_templates/cqed_ui.py
pylabnet/gui/pyqt/gui_templates/data_taker.ui
pylabnet/gui/pyqt/gui_templates/down_arrow.svg
pylabnet/gui/pyqt/gui_templates/fiber_coupling.ui
pylabnet/gui/pyqt/gui_templates/fiber_coupling_direct.ui
pylabnet/gui/pyqt/gui_templates/fit_error.ui
pylabnet/gui/pyqt/gui_templates/fit_params.ui
pylabnet/gui/pyqt/gui_templates/fit_popup.ui
pylabnet/gui/pyqt/gui_templates/fit_popup_hist.ui
pylabnet/gui/pyqt/gui_templates/fit_ui.py
pylabnet/gui/pyqt/gui_templates/fitting_scan_1d.ui
pylabnet/gui/pyqt/gui_templates/green_LED_off.svg
pylabnet/gui/pyqt/gui_templates/green_LED_on.svg
pylabnet/gui/pyqt/gui_templates/histogram - Copy.ui
pylabnet/gui/pyqt/gui_templates/histogram.ui
pylabnet/gui/pyqt/gui_templates/imaging_green.ui
pylabnet/gui/pyqt/gui_templates/left_arrow.svg
pylabnet/gui/pyqt/gui_templates/load_pulseblock.svg
pylabnet/gui/pyqt/gui_templates/logger_remote.ui
pylabnet/gui/pyqt/gui_templates/lor_fit_params.ui
pylabnet/gui/pyqt/gui_templates/positioner_control.ui
pylabnet/gui/pyqt/gui_templates/power_stabilizer.ui
pylabnet/gui/pyqt/gui_templates/pulsemaster.ui
pylabnet/gui/pyqt/gui_templates/red_LED_off.svg
pylabnet-1.0.0.dist-info/LICENSE.txt
pylabnet-1.0.0.dist-info/METADATA
pylabnet-1.0.0.dist-info/WHEEL
pylabnet-1.0.0.dist-info/entry_points.txt
pylabnet-1.0.0.dist-info/top_level.txt
pylabnet-1.0.0.dist-info/RECORD
