Metadata-Version: 2.1
Name: pylabnet
Version: 1.0.0
Summary: Client-server, python-based laboratory software
Home-page: https://github.com/lukingroup/pylabnet
Author: Lukin SiV Team
Author-email: b16lukin@gmail.com
License: MIT
Platform: UNKNOWN
Classifier: Development Status :: 3 - Alpha
Classifier: Intended Audience :: Science/Research
Classifier: License :: OSI Approved :: MIT License
Classifier: Operating System :: Microsoft :: Windows :: Windows 10
Classifier: Programming Language :: Python :: 3
Classifier: Topic :: Scientific/Engineering :: Physics
Requires-Python: >=3.7
Requires-Dist: debugpy (>=1.3.0)
Requires-Dist: decorator (>=4.4.0)
Requires-Dist: ipywidgets (>=7.5.1)
Requires-Dist: matplotlib (>=3.1.3)
Requires-Dist: netifaces (>=0.10.9)
Requires-Dist: nidaqmx (>=0.5.7)
Requires-Dist: numpy (>=1.16.5)
Requires-Dist: paramiko (>=2.7.2)
Requires-Dist: plotly (>=4.7.1)
Requires-Dist: PyQt5 (>=5.13.0)
Requires-Dist: pyqtgraph (>=0.10.0)
Requires-Dist: pyserial (>=3.4)
Requires-Dist: python-decouple (>=3.3)
Requires-Dist: python-kasa (>=0.4.0.dev2)
Requires-Dist: pytz (>=2019.3)
Requires-Dist: PyVISA (>=1.10.1)
Requires-Dist: qdarkstyle (>=2.8.1)
Requires-Dist: rpyc (>=4.1.2)
Requires-Dist: scipy (>=1.6.1)
Requires-Dist: si-prefix (>=1.2.2)
Requires-Dist: simpleeval (>=0.9.10)
Requires-Dist: slack-sdk (>=3.5.0)
